flask_file_bridge/__init__.py
flask_file_bridge/exporter.py
flask_file_bridge/importer.py
Flask_File_Bridge-1.0.1.dist-info/LICENSE
Flask_File_Bridge-1.0.1.dist-info/METADATA
Flask_File_Bridge-1.0.1.dist-info/WHEEL
Flask_File_Bridge-1.0.1.dist-info/top_level.txt
Flask_File_Bridge-1.0.1.dist-info/RECORD
