Metadata-Version: 2.1
Name: Flask-File-Bridge
Version: 1.0.1
Summary: A library for importing and exporting data from Excel and CSV files using Flask ORM.
Home-page: https://github.com/dmmuralitharan/Flask-File-Bridge
Author: Muralitharan
Author-email: dmmuralitharan@gmail.com
Classifier: Programming Language :: Python :: 3
Classifier: License :: OSI Approved :: MIT License
Classifier: Operating System :: OS Independent
Requires-Python: >=3.6
License-File: LICENSE
Requires-Dist: Flask
Requires-Dist: Flask-SQLAlchemy
Requires-Dist: pandas
Requires-Dist: openpyxl
